array_api/_2022_12.py
array_api/_2023_12.py
array_api/_2024_12.py
array_api/__init__.py
array_api/__main__.py
array_api/_draft.py
array_api/py.typed
array_api/cli/__init__.py
array_api/cli/_main.py
array_api/cli/cli.py
array_api_compat/__init__.pyi
types_array_api-1.1.5.dist-info/licenses/LICENSE
types_array_api-1.1.5.dist-info/licenses/LICENSE-MIT
types_array_api-1.1.5.dist-info/METADATA
types_array_api-1.1.5.dist-info/WHEEL
types_array_api-1.1.5.dist-info/entry_points.txt
types_array_api-1.1.5.dist-info/top_level.txt
types_array_api-1.1.5.dist-info/RECORD
